momoya/__init__.py
momoya/cli.py
momoya/core/__init__.py
momoya/core/base_extractor.py
momoya/extractors/__init__.py
momoya/extractors/sora_extractor.py
momoya-1.1.0.dist-info/licenses/LICENSE
momoya-1.1.0.dist-info/METADATA
momoya-1.1.0.dist-info/WHEEL
momoya-1.1.0.dist-info/entry_points.txt
momoya-1.1.0.dist-info/top_level.txt
momoya-1.1.0.dist-info/RECORD
