Metadata-Version: 2.4
Name: momoya
Version: 1.1.0
Summary: A package for extracting AI-generated images and videos from various platforms
Home-page: https://github.com/deidax/momoya
Author: deidax
Author-email: deidaxtech@gmail.com
License: MIT
Keywords: Scraping,AI,Images,Videos
Classifier: Programming Language :: Python :: 3
Classifier: License :: OSI Approved :: MIT License
Classifier: Operating System :: OS Independent
Requires-Python: >=3.10
License-File: LICENSE
Requires-Dist: aiohttp==3.8.0
Requires-Dist: aiofiles==0.8.0
Requires-Dist: pyfiglet==0.8.post1
Requires-Dist: termcolor==1.1.0
Dynamic: author
Dynamic: author-email
Dynamic: classifier
Dynamic: description
Dynamic: description-content-type
Dynamic: home-page
Dynamic: keywords
Dynamic: license
Dynamic: license-file
Dynamic: requires-dist
Dynamic: requires-python
Dynamic: summary
